uniprotpy/__init__.py
uniprotpy/extract_proteomes.py
uniprotpy/protein_tree.py
uniprotpy/select_best_proteome.py
uniprotpy/shell.py
uniprotpy/taxon_tree.py
uniprotpy/version.py
uniprotpy-0.0.1.dist-info/METADATA
uniprotpy-0.0.1.dist-info/WHEEL
uniprotpy-0.0.1.dist-info/entry_points.txt
uniprotpy-0.0.1.dist-info/top_level.txt
uniprotpy-0.0.1.dist-info/RECORD
