Metadata-Version: 2.1
Name: uniprotpy
Version: 0.0.1
Summary: A Python library that interfaces with UniProt data.
Home-page: https://github.com/danielmarrama/uniprotpy
Author: Daniel Marrama
Author-email: danielmarrama@gmail.com
Requires-Dist: pandas (>=1.1)
Requires-Dist: biopython (>=1.5)
